mcp_server/__init__.py
mcp_server/client.py
mcp_server/server.py
iflow_mcp_ruslanmv_simple_mcp_server_with_python-1.0.2.dist-info/METADATA
iflow_mcp_ruslanmv_simple_mcp_server_with_python-1.0.2.dist-info/WHEEL
iflow_mcp_ruslanmv_simple_mcp_server_with_python-1.0.2.dist-info/entry_points.txt
iflow_mcp_ruslanmv_simple_mcp_server_with_python-1.0.2.dist-info/RECORD
