Metadata-Version: 2.4
Name: iflow-mcp_ruslanmv_simple-mcp-server-with-python
Version: 1.0.2
Summary: A simple MCP server in Python using the MCP Python SDK
Requires-Python: >=3.7
Requires-Dist: mcp[cli]==1.6.0
